xxh_xxh/__init__.py
xxh_xxh/config.xxhc
xxh_xxh/shell.py
xxh_xxh/xxh.bash
xxh_xxh/xxh.py
xxh_xxh/xxh.xsh
xxh_xxh/xxh.zsh
xxh_xxh-0.8.14.data/scripts/xxh
xxh_xxh-0.8.14.data/scripts/xxh.bash
xxh_xxh-0.8.14.data/scripts/xxh.xsh
xxh_xxh-0.8.14.data/scripts/xxh.zsh
xxh_xxh-0.8.14.dist-info/LICENSE
xxh_xxh-0.8.14.dist-info/METADATA
xxh_xxh-0.8.14.dist-info/WHEEL
xxh_xxh-0.8.14.dist-info/top_level.txt
xxh_xxh-0.8.14.dist-info/RECORD
