Metadata-Version: 2.1
Name: xxh-xxh
Version: 0.8.14
Summary: Bring your favorite shell wherever you go through the ssh
Author-email: xxh <author@example.com>
License: BSD
Project-URL: Documentation, https://github.com/xxh/xxh/blob/master/README.md
Project-URL: Code, https://github.com/xxh/xxh
Project-URL: Issue tracker, https://github.com/xxh/xxh/issues
Classifier: Programming Language :: Python :: 3
Classifier: Programming Language :: Unix Shell
Classifier: Topic :: System :: Shells
Classifier: Topic :: System :: System Shells
Classifier: Topic :: Terminals
Classifier: Topic :: System :: Networking
Classifier: License :: OSI Approved :: BSD License
Requires-Python: >=3.6
License-File: LICENSE
Requires-Dist: pexpect >=4.8.0
Requires-Dist: pyyaml
